flask_peewee/__init__.py
flask_peewee/_compat.py
flask_peewee/_wtforms_compat.py
flask_peewee/admin.py
flask_peewee/auth.py
flask_peewee/db.py
flask_peewee/exceptions.py
flask_peewee/filters.py
flask_peewee/forms.py
flask_peewee/rest.py
flask_peewee/serializer.py
flask_peewee/utils.py
flask_peewee/static/css/admin.css
flask_peewee/static/css/bootstrap-responsive.css
flask_peewee/static/css/bootstrap-responsive.min.css
flask_peewee/static/css/bootstrap.css
flask_peewee/static/css/bootstrap.min.css
flask_peewee/static/css/bootstrap.min.responsive.css
flask_peewee/static/css/chosen-sprite.png
flask_peewee/static/css/chosen.css
flask_peewee/static/css/datepicker.css
flask_peewee/static/img/glyphicons-halflings-white.png
flask_peewee/static/img/glyphicons-halflings.png
flask_peewee/static/js/admin.js
flask_peewee/static/js/ajax-chosen.min.js
flask_peewee/static/js/bootstrap-datepicker.js
flask_peewee/static/js/bootstrap.js
flask_peewee/static/js/bootstrap.min.js
flask_peewee/static/js/chosen.jquery.min.js
flask_peewee/static/js/events.js
flask_peewee/static/js/jquery.min.js
flask_peewee/static/js/modernizr-1.5.min.js
flask_peewee/templates/base.html
flask_peewee/templates/admin/base.html
flask_peewee/templates/admin/index.html
flask_peewee/templates/admin/includes/filter_dropdown.html
flask_peewee/templates/admin/includes/filter_widgets.html
flask_peewee/templates/admin/includes/form_raw_id.html
flask_peewee/templates/admin/includes/pagination.html
flask_peewee/templates/admin/models/add.html
flask_peewee/templates/admin/models/base.html
flask_peewee/templates/admin/models/base_filters.html
flask_peewee/templates/admin/models/base_forms.html
flask_peewee/templates/admin/models/delete.html
flask_peewee/templates/admin/models/edit.html
flask_peewee/templates/admin/models/export.html
flask_peewee/templates/admin/models/index.html
flask_peewee/templates/admin/panels/base.html
flask_peewee/templates/admin/panels/default.html
flask_peewee/templates/auth/login.html
flask_peewee-3.1.0.dist-info/licenses/LICENSE
flask_peewee-3.1.0.dist-info/METADATA
flask_peewee-3.1.0.dist-info/WHEEL
flask_peewee-3.1.0.dist-info/top_level.txt
flask_peewee-3.1.0.dist-info/RECORD
