Metadata-Version: 2.4
Name: flask-peewee
Version: 3.1.0
Summary: flask admin, api, auth, forms and more with peewee
Author-email: Charles Leifer <coleifer@gmail.com>
Project-URL: Repository, https://github.com/coleifer/flask-peewee
Project-URL: Documentation, https://flask-peewee.readthedocs.io/
Classifier: Environment :: Web Environment
Classifier: Programming Language :: Python :: 2
Classifier: Programming Language :: Python :: 3
Classifier: Topic :: Internet :: WWW/HTTP :: Dynamic Content
Classifier: Topic :: Software Development :: Libraries :: Python Modules
License-File: LICENSE
Requires-Dist: flask
Requires-Dist: peewee>=3.0.0
Dynamic: license-file
